dapi/__init__.py
dapi/apps.py
dapi/auth.py
dapi/client.py
dapi/db/__init__.py
dapi/db/accessor.py
dapi/db/config.py
dapi/db/db.py
dapi/exceptions.py
dapi/files.py
dapi/jobs.py
dapi/systems.py
dapi-0.4.9.dist-info/AUTHORS.md
dapi-0.4.9.dist-info/LICENSE.md
dapi-0.4.9.dist-info/METADATA
dapi-0.4.9.dist-info/WHEEL
dapi-0.4.9.dist-info/RECORD
