Metadata-Version: 2.3
Name: dapi
Version: 0.4.9
Summary: DesignSafe API
Author: Krishna Kumar
Author-email: krishnak@utexas.edu
Requires-Python: >=3.9,<4.0
Classifier: Programming Language :: Python :: 3
Classifier: Programming Language :: Python :: 3.9
Classifier: Programming Language :: Python :: 3.10
Classifier: Programming Language :: Python :: 3.11
Classifier: Programming Language :: Python :: 3.12
Classifier: Programming Language :: Python :: 3.13
Requires-Dist: exceptiongroup (>=1.3.0,<2.0.0) ; python_version < "3.11"
Requires-Dist: griffe (>=1.7.3,<2.0.0)
Requires-Dist: jsonschema (>=4.24.0,<5.0.0)
Requires-Dist: mkdocs (>=1.6.1,<2.0.0)
Requires-Dist: mkdocs-autorefs (>=1.4.2,<2.0.0)
Requires-Dist: mkdocs-material (>=9.6.14,<10.0.0)
Requires-Dist: mkdocstrings (>=0.29.1,<0.30.0)
Requires-Dist: mkdocstrings-python (>=1.16.12,<2.0.0)
Requires-Dist: numpy (>=1.21.0) ; python_version >= "3.10"
Requires-Dist: numpy (>=1.21.0,<2.0) ; python_version == "3.9"
Requires-Dist: pandas (>=1.3.0,<3.0.0) ; python_version == "3.9"
Requires-Dist: pandas (>=2.1.0) ; python_version >= "3.10"
Requires-Dist: pymysql (>=1.1.1,<2.0.0)
Requires-Dist: python-dotenv (>=1.1.0,<2.0.0)
Requires-Dist: sqlalchemy (>=2.0.41,<3.0.0)
Requires-Dist: tapipy (>=1.8.4,<2.0.0)
Requires-Dist: tqdm (>=4.67.1,<5.0.0)
